neodroid/__init__.py
neodroid/entry_points/__init__.py
neodroid/entry_points/action_space_sampling.py
neodroid/entry_points/cli.py
neodroid/entry_points/image_batch_observation_plot.py
neodroid/entry_points/image_observation_plot.py
neodroid/entry_points/keyboard/__init__.py
neodroid/entry_points/keyboard/qweasd_input.py
neodroid/environments/__init__.py
neodroid/environments/environment.py
neodroid/environments/networking_environment.py
neodroid/environments/droid_environment/__init__.py
neodroid/environments/droid_environment/unity_environment.py
neodroid/environments/droid_environment/vector_unity_environment.py
neodroid/environments/droid_environment/deprecated/__init__.py
neodroid/environments/droid_environment/deprecated/batched_unity_environments.py
neodroid/environments/droid_environment/deprecated/single_unity_environment.py
neodroid/environments/exclude/__init__.py
neodroid/environments/exclude/blender_environment/__init__.py
neodroid/environments/exclude/blender_environment/blender_environment.py
neodroid/environments/exclude/cryengine_environment/__init__.py
neodroid/environments/exclude/godot_environment/__init__.py
neodroid/environments/exclude/minecraft_environment/__init__.py
neodroid/environments/exclude/pyboy_environment/__init__.py
neodroid/environments/exclude/pyboy_environment/a.py
neodroid/environments/exclude/pyboy_environment/gamewrapper_mario.py
neodroid/environments/exclude/pyboy_environment/gamewrapper_tetris.py
neodroid/environments/exclude/pybullet_environment/__init__.py
neodroid/environments/exclude/unreal_environment/__init__.py
neodroid/environments/exclude/vtek_environment/__init__.py
neodroid/environments/exclude/web_environment/__init__.py
neodroid/environments/gym_environment/__init__.py
neodroid/environments/gym_environment/action_encoding.py
neodroid/environments/gym_environment/gym_wrapper.py
neodroid/environments/gym_environment/vector_gym_environment.py
neodroid/environments/python_environment/__init__.py
Neodroid-0.4.9.dist-info/LICENSE.md
Neodroid-0.4.9.dist-info/METADATA
Neodroid-0.4.9.dist-info/WHEEL
Neodroid-0.4.9.dist-info/entry_points.txt
Neodroid-0.4.9.dist-info/top_level.txt
Neodroid-0.4.9.dist-info/RECORD
