Metadata-Version: 2.1
Name: Neodroid
Version: 0.4.9
Summary: Python interface for the Neodroid platform, an API for communicating with a Unity Game process for a feedback response loop
Home-page: https://github.com/sintefneodroid/neo
Author: Christian Heider Nielsen
Author-email: christian.heider@alexandra.dk
Maintainer: Christian Heider Nielsen
Maintainer-email: christian.heider@alexandra.dk
License: Apache License, Version 2.0
Download-URL: https://github.com/sintefneodroid/neo/releases
Keywords: python reinforcement-learning interface api
Platform: UNKNOWN
Classifier: Development Status :: 4 - Beta
Classifier: Environment :: Console
Classifier: Intended Audience :: End Users/Desktop
Classifier: Intended Audience :: Developers
Classifier: License :: OSI Approved :: Apache Software License
Classifier: Operating System :: MacOS :: MacOS X
Classifier: Operating System :: Microsoft :: Windows
Classifier: Operating System :: POSIX
Classifier: Operating System :: OS Independent
Classifier: Programming Language :: Python :: 3
Classifier: Natural Language :: English
Requires-Python: >=3.6
Requires-Dist: devpack
Requires-Dist: flatbuffers
Requires-Dist: pyfiglet
Requires-Dist: fire
Requires-Dist: pyzmq
Requires-Dist: numpy
Requires-Dist: Pillow
Requires-Dist: tqdm
Requires-Dist: matplotlib
Requires-Dist: cloudpickle
Requires-Dist: imageio
Requires-Dist: pip
Provides-Extra: all
Requires-Dist: pip (>=19.0.3) ; extra == 'all'
Requires-Dist: wheel (>=0.33.0) ; extra == 'all'
Requires-Dist: twine (>=1.13.0) ; extra == 'all'
Requires-Dist: pytest (>=4.3.0) ; extra == 'all'
Requires-Dist: pytest-cov (>=2.6.1) ; extra == 'all'
Requires-Dist: coveralls (>=1.6.0) ; extra == 'all'
Requires-Dist: sphinx ; extra == 'all'
Requires-Dist: m2r ; extra == 'all'
Requires-Dist: sphinxcontrib-programoutput ; extra == 'all'
Requires-Dist: gym ; extra == 'all'
Requires-Dist: pytest (>=4.4.1) ; extra == 'all'
Requires-Dist: kivy (>=1.10.1) ; extra == 'all'
Provides-Extra: dev
Requires-Dist: pip (>=19.0.3) ; extra == 'dev'
Requires-Dist: wheel (>=0.33.0) ; extra == 'dev'
Requires-Dist: twine (>=1.13.0) ; extra == 'dev'
Requires-Dist: pytest (>=4.3.0) ; extra == 'dev'
Requires-Dist: pytest-cov (>=2.6.1) ; extra == 'dev'
Requires-Dist: coveralls (>=1.6.0) ; extra == 'dev'
Provides-Extra: docs
Requires-Dist: sphinx ; extra == 'docs'
Requires-Dist: m2r ; extra == 'docs'
Requires-Dist: sphinxcontrib-programoutput ; extra == 'docs'
Provides-Extra: gui
Requires-Dist: kivy (>=1.10.1) ; extra == 'gui'
Provides-Extra: tests
Requires-Dist: pytest (>=4.4.1) ; extra == 'tests'
Provides-Extra: wrappers
Requires-Dist: gym ; extra == 'wrappers'
